{"ext":{},"sticker":[{"type_background":"Color","color_background":-1,"width":1220,"type":"background","matrix":"1.0,0.0,0.0,0.0,1.0,0.0,0.0,0.0,1.0","height":1220},{"size_border":0,"rotate":-0,"originHeight":300,"color_fill":0,"originWidth":300,"opacity_border":255,"isPhoto":false,"type":"drawable","matrix":"1.1931988,0.0,431.5999,0.0,1.1931988,274.57416,0.0,0.0,1.0","color_border":0,"url":"https://raw.githubusercontent.com/votaminh/cdn.msc.logo/main/graphic_template/logo-template-graphic/animal-pet/animal-pet-1459.svg","isLock":false,"lineStyle":0,"currentWidth":300,"matrixCrop":"1.0,0.0,0.0,0.0,1.0,0.0,0.0,0.0,1.0","currentHeight":330,"rectCrop":"0,000000|0,000000|300,000000|330,000000","id":1728871691084,"opacity":255,"thumbUrl":"https://raw.githubusercontent.com/votaminh/cdn.msc.logo/main/graphic_template/logo-template-graphic/animal-pet/animal-pet-1459.svg","svgGradientConfig":{"svgGradients":[],"svgFillColors":[]}},{"opacityShadow":255,"rotate":-0,"isUnderline":false,"curve":0,"fontUrl":"https://raw.githubusercontent.com/votaminh/cdn.font.graphic/main/font_file4/YACgEQNAr7wMontserrat-BoldBOLDBold","type":"text","matrix":"1.857632,0.0,158.86961,0.0,1.857632,725.8623,0.0,0.0,1.0","content":"Company Name","inputContent":"Company Name","isItalic":false,"offsetX":10,"isLock":false,"blurShadow":80,"spacing":0,"offsetY":5,"sizePx":60,"rectCrop":"1,000000|12,000000|486,000000|66,000000","id":1728871713791,"colorText":-14343128,"opacityBorder":255,"sizeBorder":5,"colorBorder":0,"isBold":false,"fontName":"YACgEQNAr7w!Montserrat-Bold!BOLD!Bold","isLower":true,"colorShadow":0,"textOpacity":255,"lineHeight":8,"alignment":2,"borderPosition":0},{"opacityShadow":255,"rotate":-0,"isUnderline":false,"curve":0,"fontUrl":"https://raw.githubusercontent.com/votaminh/cdn.font.graphic/main/font_file4/YADLjI9qxTAMontserrat-RegularREGULARRegular","type":"text","matrix":"0.8183136,0.0,406.23987,0.0,0.8183136,889.0486,0.0,0.0,1.0","content":"SLOGAN HERE","inputContent":"Slogan Here","isItalic":false,"offsetX":10,"isLock":false,"blurShadow":80,"spacing":0.07999999821186066,"offsetY":5,"sizePx":60,"rectCrop":"4,000000|0,000000|494,000000|41,000000","id":1728871737258,"colorText":-14343128,"opacityBorder":255,"sizeBorder":5,"colorBorder":0,"isBold":false,"fontName":"YADLjI9qxTA!Montserrat-Regular!REGULAR!Regular","isLower":false,"colorShadow":0,"textOpacity":255,"lineHeight":8,"alignment":2,"borderPosition":0}],"width":1220,"id":"alphabet-z-and-zebra-stripe","height":1220}