{"id":"pug-and-wrench","sticker":[{"type":"background","type_background":"Color","width":1220,"height":1220,"color_background":-1,"matrix":"1.0,0.0,0.0,0.0,1.0,0.0,0.0,0.0,1.0"},{"type":"shape","shapeType":0,"opacity":255,"color":-16777216,"opacityBorder":255,"colorBorder":0,"sizeBorder":0,"corner":0,"lineStyle":0,"rectBound":"0,000000|455,717163|610,000000|545,703430","id":1738722774939,"matrix":"0.79904914,0.0,361.22855,0.0,0.79904914,205.44946,0.0,0.0,1.0"},{"type":"drawable","color_fill":0,"opacity":255,"color_border":0,"size_border":0,"opacity_border":255,"isPhoto":false,"url":"https:\/\/raw.githubusercontent.com\/votaminh\/cdn.msc.logo\/main\/graphic_template\/logo-template-graphic\/animal-pet\/animal-pet-2016.svg","thumbUrl":"https:\/\/raw.githubusercontent.com\/votaminh\/cdn.msc.logo\/main\/graphic_template\/logo-template-graphic\/animal-pet\/animal-pet-2016.svg","matrix":"1.0,0.0,396.1704,0.0,1.0,225.6149,0.0,0.0,1.0","id":1738722771082,"rotate":-0,"originWidth":300,"originHeight":300,"currentWidth":427,"currentHeight":397,"lineStyle":0,"svgGradientConfig":{"svgGradients":[],"svgFillColors":[]},"rectCrop":"0,000000|0,000000|427,000000|397,000000","matrixCrop":"1.0,0.0,0.0,0.0,1.0,0.0,0.0,0.0,1.0","isLock":false},{"type":"text","content":"LOGO NAME","inputContent":"LOGO NAME","sizePx":60,"fontName":"YACgEYS9sJU!AlfaSlabOne-Regular!REGULAR!Regular","fontUrl":"https:\/\/raw.githubusercontent.com\/votaminh\/cdn.font.graphic\/main\/font_file4\/YACgEYS9sJUAlfaSlabOne-RegularREGULARRegular","alignment":2,"isLower":false,"isBold":false,"isUnderline":false,"isItalic":false,"spacing":0.12999999523162842,"lineHeight":8,"colorShadow":0,"blurShadow":80,"opacityShadow":255,"offsetX":10,"offsetY":5,"borderPosition":0,"colorBorder":0,"sizeBorder":5,"opacityBorder":255,"colorText":-16645630,"isLock":false,"id":1738722806305,"rotate":-0,"matrix":"1.9034652,0.0,152.73358,0.0,1.9034652,795.04333,0.0,0.0,1.0","textOpacity":255,"rectCrop":"5,000000|1,000000|481,000000|48,000000","curve":0},{"type":"text","content":"SLOGAN HERE","inputContent":"SLOGAN HERE","sizePx":60,"fontName":"YAE5fPSY9qM!Poppins-Regular!REGULAR!Regular","fontUrl":"https:\/\/raw.githubusercontent.com\/votaminh\/cdn.font.graphic\/main\/font_file4\/YAE5fPSY9qMPoppins-RegularREGULARRegular","alignment":2,"isLower":false,"isBold":false,"isUnderline":false,"isItalic":false,"spacing":0.12999999523162842,"lineHeight":8,"colorShadow":0,"blurShadow":80,"opacityShadow":255,"offsetX":10,"offsetY":5,"borderPosition":0,"colorBorder":0,"sizeBorder":5,"opacityBorder":255,"colorText":-16645630,"isLock":false,"id":1738722807438,"rotate":-0,"matrix":"0.8855922,0.0,396.69147,0.0,0.8855922,943.78937,0.0,0.0,1.0","textOpacity":255,"rectCrop":"7,000000|0,000000|471,000000|42,000000","curve":0}],"width":1220,"height":1220,"ext":{}}