{"id":"welding-torch-and-spark","sticker":[{"type":"background","type_background":"Color","width":1220,"height":1220,"color_background":-1,"matrix":"1.0,0.0,0.0,0.0,1.0,0.0,0.0,0.0,1.0"},{"type":"drawable","color_fill":0,"opacity":255,"color_border":0,"size_border":0,"opacity_border":255,"isPhoto":false,"url":"https:\/\/raw.githubusercontent.com\/votaminh\/cdn.msc.logo\/main\/graphic_template\/logo-template-graphic\/industrial\/industrial-0256.svg","thumbUrl":"https:\/\/raw.githubusercontent.com\/votaminh\/cdn.msc.logo\/main\/graphic_template\/logo-template-graphic\/industrial\/industrial-0256.svg","matrix":"0.7789114,0.6271335,702.4575,-0.6271335,0.7789114,491.25775,0.0,0.0,1.0","id":1743125917731,"rotate":-38.838966369628906,"originWidth":300,"originHeight":300,"currentWidth":86,"currentHeight":446,"lineStyle":0,"svgGradientConfig":{"svgGradients":[],"svgFillColors":[]},"rectCrop":"0,000000|0,000000|86,000000|446,000000","matrixCrop":"1.0,0.0,0.0,0.0,1.0,0.0,0.0,0.0,1.0","isLock":false},{"type":"drawable","color_fill":0,"opacity":255,"color_border":0,"size_border":0,"opacity_border":255,"isPhoto":false,"url":"https:\/\/raw.githubusercontent.com\/votaminh\/cdn.msc.logo\/main\/graphic_template\/logo-template-graphic\/industrial\/industrial-0257.svg","thumbUrl":"https:\/\/raw.githubusercontent.com\/votaminh\/cdn.msc.logo\/main\/graphic_template\/logo-template-graphic\/industrial\/industrial-0257.svg","matrix":"1.0,0.0,478.19104,0.0,1.0,380.27954,0.0,0.0,1.0","id":1743125918370,"rotate":-0,"originWidth":300,"originHeight":300,"currentWidth":242,"currentHeight":203,"lineStyle":0,"svgGradientConfig":{"svgGradients":[],"svgFillColors":[]},"rectCrop":"0,000000|0,000000|242,000000|203,000000","matrixCrop":"1.0,0.0,0.0,0.0,1.0,0.0,0.0,0.0,1.0","isLock":false},{"type":"text","content":"LOGO NAME","inputContent":"LOGO NAME","sizePx":60,"fontName":"YACgEQY10lw!Oswald-Regular!REGULAR!Regular","fontUrl":"https:\/\/raw.githubusercontent.com\/votaminh\/cdn.font.graphic\/main\/font_file4\/YACgEQY10lwOswald-RegularREGULARRegular","alignment":2,"isLower":false,"isBold":false,"isUnderline":false,"isItalic":false,"spacing":0,"lineHeight":8,"colorShadow":0,"blurShadow":80,"opacityShadow":255,"offsetX":10,"offsetY":5,"borderPosition":0,"colorBorder":0,"sizeBorder":5,"opacityBorder":255,"colorText":-13619086,"isLock":false,"id":1743125919777,"rotate":-0,"matrix":"2.2599268,0.0,185.92194,0.0,2.2599268,623.4643,0.0,0.0,1.0","textOpacity":255,"rectCrop":"3,779297|0,600586|258,375000|50,214844","curve":0}],"width":1220,"height":1220,"ext":{}}