{"id":"flat-tiger-head","sticker":[{"type":"background","type_background":"Color","width":1220,"height":1220,"color_background":-1,"matrix":"1.0,0.0,0.0,0.0,1.0,0.0,0.0,0.0,1.0"},{"type":"drawable","color_fill":0,"opacity":255,"color_border":0,"size_border":0,"opacity_border":255,"isPhoto":false,"url":"https:\/\/raw.githubusercontent.com\/votaminh\/cdn.msc.logo\/main\/graphic_template\/logo-template-graphic\/animal-pet\/animal-pet-1351.svg","thumbUrl":"https:\/\/raw.githubusercontent.com\/votaminh\/cdn.msc.logo\/main\/graphic_template\/logo-template-graphic\/animal-pet\/animal-pet-1351.svg","matrix":"1.0,0.0,402.8272,0.0,1.0,251.32,0.0,0.0,1.0","id":1733373258981,"rotate":-0,"originWidth":300,"originHeight":300,"currentWidth":412,"currentHeight":439,"lineStyle":0,"svgGradientConfig":{"svgGradients":[],"svgFillColors":[]},"rectCrop":"0,000000|0,000000|412,000000|439,000000","matrixCrop":"1.0,0.0,0.0,0.0,1.0,0.0,0.0,0.0,1.0","isLock":false},{"type":"text","content":"COMPANY NAME","inputContent":"Company Name","sizePx":60,"fontName":"YACkoEA0Kc0!Shrikhand-Regular!REGULAR!Regular","fontUrl":"https:\/\/raw.githubusercontent.com\/votaminh\/cdn.font.graphic\/main\/font_file4\/YACkoEA0Kc0Shrikhand-RegularREGULARRegular","alignment":2,"isLower":false,"isBold":false,"isUnderline":false,"isItalic":false,"spacing":0,"lineHeight":8,"colorShadow":0,"blurShadow":80,"opacityShadow":255,"offsetX":10,"offsetY":5,"borderPosition":0,"colorBorder":0,"sizeBorder":5,"opacityBorder":255,"colorText":-9806507,"isLock":false,"id":1733373261103,"rotate":-0,"matrix":"1.8932211,0.0,126.56348,0.0,1.8932211,789.71716,0.0,0.0,1.0","textOpacity":255,"rectCrop":"3,000000|0,000000|518,000000|41,000000","curve":0},{"type":"text","content":"SLOGAN HERE","inputContent":"Slogan Here","sizePx":60,"fontName":"YACkoEA0Kc0!Shrikhand-Regular!REGULAR!Regular","fontUrl":"https:\/\/raw.githubusercontent.com\/votaminh\/cdn.font.graphic\/main\/font_file4\/YACkoEA0Kc0Shrikhand-RegularREGULARRegular","alignment":2,"isLower":false,"isBold":false,"isUnderline":false,"isItalic":false,"spacing":0.17000000178813934,"lineHeight":8,"colorShadow":0,"blurShadow":80,"opacityShadow":255,"offsetX":10,"offsetY":5,"borderPosition":0,"colorBorder":0,"sizeBorder":5,"opacityBorder":255,"colorText":-9806507,"isLock":false,"id":1733373262287,"rotate":-0,"matrix":"0.8611222,0.0,373.2605,0.0,0.8611222,914.76013,0.0,0.0,1.0","textOpacity":255,"rectCrop":"4,000000|0,000000|549,000000|41,000000","curve":0}],"width":1220,"height":1220,"ext":{}}