{"id":"pigeon-and-beautiful-lotus","sticker":[{"type":"background","type_background":"Color","width":1220,"height":1220,"color_background":-1,"matrix":"1.0,0.0,0.0,0.0,1.0,0.0,0.0,0.0,1.0"},{"type":"drawable","color_fill":0,"opacity":255,"color_border":0,"size_border":0,"opacity_border":255,"isPhoto":false,"url":"https:\/\/raw.githubusercontent.com\/votaminh\/cdn.msc.logo\/main\/graphic_template\/logo-template-graphic\/nature\/nature-1086.svg","thumbUrl":"https:\/\/raw.githubusercontent.com\/votaminh\/cdn.msc.logo\/main\/graphic_template\/logo-template-graphic\/nature\/nature-1086.svg","matrix":"0.4008414,0.9161475,51.261505,-0.9161475,0.4008414,660.25885,0.0,0.0,1.0","id":1738639339853,"rotate":-66.36920928955078,"originWidth":300,"originHeight":300,"currentWidth":305,"currentHeight":217,"lineStyle":0,"svgGradientConfig":{"svgGradients":[],"svgFillColors":[]},"rectCrop":"0,000000|0,000000|305,000000|217,000000","matrixCrop":"1.0,0.0,0.0,0.0,1.0,0.0,0.0,0.0,1.0","isLock":false},{"type":"drawable","color_fill":0,"opacity":255,"color_border":0,"size_border":0,"opacity_border":255,"isPhoto":false,"url":"https:\/\/raw.githubusercontent.com\/votaminh\/cdn.msc.logo\/main\/graphic_template\/logo-template-graphic\/nature\/nature-1087.svg","thumbUrl":"https:\/\/raw.githubusercontent.com\/votaminh\/cdn.msc.logo\/main\/graphic_template\/logo-template-graphic\/nature\/nature-1087.svg","matrix":"0.99999994,0.0,125.61931,0.0,0.99999994,457.41028,0.0,0.0,1.0","id":1738639341178,"rotate":-0,"originWidth":300,"originHeight":300,"currentWidth":312,"currentHeight":300,"lineStyle":0,"svgGradientConfig":{"svgGradients":[],"svgFillColors":[]},"rectCrop":"0,000000|0,000000|312,000000|300,000000","matrixCrop":"1.0,0.0,0.0,0.0,1.0,0.0,0.0,0.0,1.0","isLock":false},{"type":"text","content":"Logo Name","inputContent":"Logo Name","sizePx":60,"fontName":"msc-font022!Playball-Regular!REGULAR!Regular","fontUrl":"https:\/\/raw.githubusercontent.com\/votaminh\/cdn.font.graphic\/main\/font_file4\/msc-font022Playball-RegularREGULARRegular","alignment":2,"isLower":true,"isBold":false,"isUnderline":false,"isItalic":false,"spacing":0,"lineHeight":8,"colorShadow":0,"blurShadow":80,"opacityShadow":255,"offsetX":10,"offsetY":5,"borderPosition":0,"colorBorder":0,"sizeBorder":5,"opacityBorder":255,"colorText":-10216625,"isLock":false,"id":1738639349588,"rotate":-0,"matrix":"2.4312189,0.0,481.26758,0.0,2.4312189,480.72705,0.0,0.0,1.0","textOpacity":255,"rectCrop":"0,000000|13,000000|264,000000|70,000000","curve":0},{"type":"text","content":"Slogan Here","inputContent":"Slogan Here","sizePx":60,"fontName":"msc-font023!Tenali_Ramakrishna-Regular!REGULAR!Regular","fontUrl":"https:\/\/raw.githubusercontent.com\/votaminh\/cdn.font.graphic\/main\/font_file4\/msc-font023Tenali_Ramakrishna-RegularREGULARRegular","alignment":2,"isLower":true,"isBold":false,"isUnderline":false,"isItalic":false,"spacing":0.23999999463558197,"lineHeight":8,"colorShadow":0,"blurShadow":80,"opacityShadow":255,"offsetX":10,"offsetY":5,"borderPosition":0,"colorBorder":0,"sizeBorder":5,"opacityBorder":255,"colorText":-10216625,"isLock":false,"id":1738639350977,"rotate":-0,"matrix":"0.9800929,0.0,470.50732,0.0,0.9800929,672.9405,0.0,0.0,1.0","textOpacity":255,"rectCrop":"8,000000|8,000000|397,000000|46,000000","curve":0}],"width":1220,"height":1220,"ext":{}}