{"id":"white-pigeon-and-yellow-envelope","sticker":[{"type":"background","type_background":"Color","width":1220,"height":1220,"color_background":-1,"matrix":"1.0,0.0,0.0,0.0,1.0,0.0,0.0,0.0,1.0"},{"type":"drawable","color_fill":0,"opacity":255,"color_border":0,"size_border":0,"opacity_border":255,"isPhoto":false,"url":"https:\/\/raw.githubusercontent.com\/votaminh\/cdn.msc.logo\/main\/graphic_template\/logo-template-graphic\/communication\/communication-0129.svg","thumbUrl":"https:\/\/raw.githubusercontent.com\/votaminh\/cdn.msc.logo\/main\/graphic_template\/logo-template-graphic\/communication\/communication-0129.svg","matrix":"1.0,0.0,377.74744,0.0,1.0,234.8589,0.0,0.0,1.0","id":1743500146794,"rotate":-0,"originWidth":300,"originHeight":300,"currentWidth":463,"currentHeight":330,"lineStyle":0,"svgGradientConfig":{"svgGradients":[],"svgFillColors":[]},"rectCrop":"0,000000|0,000000|463,000000|330,000000","matrixCrop":"1.0,0.0,0.0,0.0,1.0,0.0,0.0,0.0,1.0","isLock":false},{"type":"drawable","color_fill":0,"opacity":255,"color_border":0,"size_border":0,"opacity_border":255,"isPhoto":false,"url":"https:\/\/raw.githubusercontent.com\/votaminh\/cdn.msc.logo\/main\/graphic_template\/logo-template-graphic\/animal-pet\/animal-pet-0818.svg","thumbUrl":"https:\/\/raw.githubusercontent.com\/votaminh\/cdn.msc.logo\/main\/graphic_template\/logo-template-graphic\/animal-pet\/animal-pet-0818.svg","matrix":"1.0,0.0,447.51562,0.0,1.0,308.82678,0.0,0.0,1.0","id":1743500147485,"rotate":-0,"originWidth":300,"originHeight":300,"currentWidth":309,"currentHeight":251,"lineStyle":0,"svgGradientConfig":{"svgGradients":[],"svgFillColors":[]},"rectCrop":"0,000000|0,000000|309,000000|251,000000","matrixCrop":"1.0,0.0,0.0,0.0,1.0,0.0,0.0,0.0,1.0","isLock":false},{"type":"drawable","color_fill":0,"opacity":255,"color_border":0,"size_border":0,"opacity_border":255,"isPhoto":false,"url":"https:\/\/raw.githubusercontent.com\/votaminh\/cdn.msc.logo\/main\/graphic_template\/logo-template-graphic\/communication\/communication-0128.svg","thumbUrl":"https:\/\/raw.githubusercontent.com\/votaminh\/cdn.msc.logo\/main\/graphic_template\/logo-template-graphic\/communication\/communication-0128.svg","matrix":"1.0,0.0,377.74744,0.0,1.0,396.35013,0.0,0.0,1.0","id":1743500148217,"rotate":-0,"originWidth":300,"originHeight":300,"currentWidth":463,"currentHeight":282,"lineStyle":0,"svgGradientConfig":{"svgGradients":[],"svgFillColors":[]},"rectCrop":"0,000000|0,000000|463,000000|282,000000","matrixCrop":"1.0,0.0,0.0,0.0,1.0,0.0,0.0,0.0,1.0","isLock":false},{"type":"text","content":"COMPANY NAME","inputContent":"COMPANY NAME","sizePx":60,"fontName":"YADK4HApyHc!Mandali!REGULAR!Regular","fontUrl":"https:\/\/raw.githubusercontent.com\/votaminh\/cdn.font.graphic\/main\/font_file4\/YADK4HApyHcMandaliREGULARRegular","alignment":2,"isLower":false,"isBold":false,"isUnderline":false,"isItalic":false,"spacing":0,"lineHeight":8,"colorShadow":0,"blurShadow":80,"opacityShadow":255,"offsetX":10,"offsetY":5,"borderPosition":0,"colorBorder":0,"sizeBorder":5,"opacityBorder":255,"colorText":-12699849,"isLock":false,"id":1743500149956,"rotate":-0,"matrix":"1.9452815,0.0,123.294044,0.0,1.9452815,781.5028,0.0,0.0,1.0","textOpacity":255,"rectCrop":"3,500977|0,600586|495,120117|43,359375","curve":0},{"type":"text","content":"SLOGAN HERE","inputContent":"SLOGAN HERE","sizePx":60,"fontName":"YADK4HApyHc!Mandali!REGULAR!Regular","fontUrl":"https:\/\/raw.githubusercontent.com\/votaminh\/cdn.font.graphic\/main\/font_file4\/YADK4HApyHcMandaliREGULARRegular","alignment":2,"isLower":false,"isBold":false,"isUnderline":false,"isItalic":false,"spacing":0.09000000357627869,"lineHeight":8,"colorShadow":0,"blurShadow":80,"opacityShadow":255,"offsetX":10,"offsetY":5,"borderPosition":0,"colorBorder":0,"sizeBorder":5,"opacityBorder":255,"colorText":-12699849,"isLock":false,"id":1743500151511,"rotate":-0,"matrix":"0.7808333,0.0,422.73987,0.0,0.7808333,912.1848,0.0,0.0,1.0","textOpacity":255,"rectCrop":"6,274219|0,600586|474,820099|43,359375","curve":0}],"width":1220,"height":1220,"ext":{}}