{"ext":{},"sticker":[{"type_background":"Color","color_background":-1,"width":1220,"type":"background","matrix":"1.0,0.0,0.0,0.0,1.0,0.0,0.0,0.0,1.0","height":1220},{"size_border":0,"rotate":-0,"originHeight":300,"color_fill":0,"originWidth":300,"opacity_border":255,"isPhoto":false,"type":"drawable","matrix":"1.3831981,0.0,402.52045,0.0,1.3831981,254.2193,0.0,0.0,1.0","color_border":0,"url":"https://raw.githubusercontent.com/votaminh/cdn.msc.logo/main/graphic_template/logo-template-graphic/art-entertainment/art-entertainment-968.svg","isLock":false,"lineStyle":0,"currentWidth":300,"matrixCrop":"1.0,0.0,0.0,0.0,1.0,0.0,0.0,0.0,1.0","currentHeight":279,"rectCrop":"0,000000|0,000000|300,000000|279,000000","id":1729571736740,"opacity":255,"thumbUrl":"https://raw.githubusercontent.com/votaminh/cdn.msc.logo/main/graphic_template/logo-template-graphic/art-entertainment/art-entertainment-968.svg","svgGradientConfig":{"svgGradients":[{"color1":"#1E1C19","color2":"#5E5449","y1":"1.0","x1":"0.5073743","y2":"0.013544588","x2":"0.5084427","offset2":"100.0%","id":"grad1729571778103","offset1":"0.0%"}],"svgFillColors":[{"fillColor":"grad1729571778103","targetColorHex":"#0A0A0A"}]}},{"size_border":0,"rotate":-0,"originHeight":300,"color_fill":0,"originWidth":300,"opacity_border":255,"isPhoto":false,"type":"drawable","matrix":"0.6055041,0.0,520.502,0.0,0.6055041,585.6362,0.0,0.0,1.0","color_border":0,"url":"https://raw.githubusercontent.com/votaminh/cdn.msc.logo/main/graphic_template/logo-template-graphic/art-entertainment/art-entertainment-969.svg","isLock":false,"lineStyle":0,"currentWidth":300,"matrixCrop":"1.0,0.0,0.0,0.0,1.0,0.0,0.0,0.0,1.0","currentHeight":180,"rectCrop":"0,000000|0,000000|300,000000|180,000000","id":1729571780270,"opacity":255,"thumbUrl":"https://raw.githubusercontent.com/votaminh/cdn.msc.logo/main/graphic_template/logo-template-graphic/art-entertainment/art-entertainment-969.svg","svgGradientConfig":{"svgGradients":[{"color1":"#1E1C19","color2":"#5E5449","y1":"0.9164726","x1":"0.5081401","y2":"0.04612797","x2":"0.550775","offset2":"100.0%","id":"grad1729571801484","offset1":"0.0%"}],"svgFillColors":[{"fillColor":"grad1729571801484","targetColorHex":"#0A0A0A"}]}},{"size_border":0,"rotate":-0,"originHeight":300,"color_fill":0,"originWidth":300,"opacity_border":255,"isPhoto":false,"type":"drawable","matrix":"0.45725566,0.0,551.61145,0.0,0.45725566,378.86646,0.0,0.0,1.0","color_border":0,"url":"https://raw.githubusercontent.com/votaminh/cdn.msc.logo/main/graphic_template/logo-template-graphic/crown/crown-0152.svg","isLock":false,"lineStyle":0,"currentWidth":300,"matrixCrop":"1.0,0.0,0.0,0.0,1.0,0.0,0.0,0.0,1.0","currentHeight":207,"rectCrop":"0,000000|0,000000|300,000000|207,000000","id":1729571803764,"opacity":255,"thumbUrl":"https://raw.githubusercontent.com/votaminh/cdn.msc.logo/main/graphic_template/logo-template-graphic/crown/crown-0152.svg","svgGradientConfig":{"svgGradients":[],"svgFillColors":[]}},{"size_border":0,"rotate":-0,"originHeight":300,"color_fill":0,"originWidth":300,"opacity_border":255,"isPhoto":false,"type":"drawable","matrix":"4.850132,0.0,-114.46821,0.0,4.850132,933.37317,0.0,0.0,1.0","color_border":0,"url":"https://raw.githubusercontent.com/votaminh/cdn.msc.logo/main/graphic_template/logo-template-graphic/linelae/linelae-0582.svg","isLock":false,"lineStyle":0,"currentWidth":300,"matrixCrop":"1.0,0.0,0.0,0.0,1.0,0.0,0.0,0.0,1.0","currentHeight":1,"rectCrop":"0,000000|0,000000|300,000000|1,000000","id":1729571820411,"opacity":255,"thumbUrl":"https://raw.githubusercontent.com/votaminh/cdn.msc.logo/main/graphic_template/logo-template-graphic/linelae/linelae-0582.svg","svgGradientConfig":{"svgGradients":[],"svgFillColors":[]}},{"opacityShadow":255,"rotate":-0,"isUnderline":false,"curve":0,"fontUrl":"https://raw.githubusercontent.com/votaminh/cdn.font.graphic/main/font_file4/msc-font021Orbitron-BoldBOLDBold","type":"text","matrix":"1.8728896,0.0,219.13206,0.0,1.8728896,792.2317,0.0,0.0,1.0","content":"LOGO NAME","inputContent":"Logo Name","isItalic":false,"offsetX":10,"isLock":false,"blurShadow":80,"spacing":0,"offsetY":5,"sizePx":60,"rectCrop":"3,000000|0,000000|414,000000|42,000000","id":1729571859085,"colorText":-13290185,"opacityBorder":255,"sizeBorder":5,"colorBorder":0,"isBold":false,"fontName":"msc-font021!Orbitron-Bold!BOLD!Bold","isLower":false,"colorShadow":0,"textOpacity":255,"lineHeight":8,"alignment":2,"borderPosition":0},{"opacityShadow":255,"rotate":-0,"isUnderline":false,"curve":0,"fontUrl":"https://raw.githubusercontent.com/votaminh/cdn.font.graphic/main/font_file4/msc-font020Numans-RegularREGULARRegular","type":"text","matrix":"0.80023474,0.0,380.9845,0.0,0.80023474,916.3048,0.0,0.0,1.0","content":"SLOGAN HERE","inputContent":"Slogan Here","isItalic":false,"offsetX":10,"isLock":false,"blurShadow":80,"spacing":0.20999999344348907,"offsetY":5,"sizePx":60,"rectCrop":"9,000000|0,000000|571,000000|43,000000","id":1729571886782,"colorText":-13290185,"opacityBorder":255,"sizeBorder":5,"colorBorder":0,"isBold":false,"fontName":"msc-font020!Numans-Regular!REGULAR!Regular","isLower":false,"colorShadow":0,"textOpacity":255,"lineHeight":8,"alignment":2,"borderPosition":0}],"width":1220,"id":"black-and-white-crown-and-ace","height":1220}