{"id":"simple-nail-polish-logo","sticker":[{"type":"background","type_background":"Color","width":1220,"height":1220,"color_background":-1,"matrix":"1.0,0.0,0.0,0.0,1.0,0.0,0.0,0.0,1.0"},{"type":"shape","shapeType":1,"opacity":255,"color":0,"opacityBorder":255,"colorBorder":0,"sizeBorder":0,"corner":0,"lineStyle":0,"rectBound":"0,000000|0,000000|610,000000|610,000000","id":1742292750423,"matrix":"2.006134,0.0,0.0,0.0,2.006134,0.0,0.0,0.0,1.0","gradient":{"startColor":-793662,"endColor":-4413297,"offset1":0,"offset2":100,"percentX1":0.9775703549385071,"percentY1":0.4874904155731201,"percentX2":-0.0362684465944767,"percentY2":0.491096168756485}},{"type":"drawable","color_fill":0,"opacity":255,"color_border":0,"size_border":0,"opacity_border":255,"isPhoto":false,"url":"https:\/\/raw.githubusercontent.com\/votaminh\/cdn.msc.logo\/main\/graphic_template\/logo-template-graphic\/fashion-beauty\/fashion-beauty-1000.svg","thumbUrl":"https:\/\/raw.githubusercontent.com\/votaminh\/cdn.msc.logo\/main\/graphic_template\/logo-template-graphic\/fashion-beauty\/fashion-beauty-1000.svg","matrix":"1.0,0.0,495.31998,0.0,1.0,209.87265,0.0,0.0,1.0","id":1742292795093,"rotate":-0,"originWidth":300,"originHeight":300,"currentWidth":229,"currentHeight":444,"lineStyle":0,"svgGradientConfig":{"svgGradients":[],"svgFillColors":[]},"rectCrop":"0,000000|0,000000|229,000000|444,000000","matrixCrop":"1.0,0.0,0.0,0.0,1.0,0.0,0.0,0.0,1.0","isLock":false},{"type":"text","content":"Company Name","inputContent":"Company Name","sizePx":60,"fontName":"YACgEesdoec!LobsterTwo!REGULAR!Regular","fontUrl":"https:\/\/raw.githubusercontent.com\/votaminh\/cdn.font.graphic\/main\/font_file4\/YACgEesdoecLobsterTwoREGULARRegular","alignment":2,"isLower":true,"isBold":false,"isUnderline":false,"isItalic":false,"spacing":0,"lineHeight":8,"colorShadow":0,"blurShadow":80,"opacityShadow":255,"offsetX":10,"offsetY":5,"borderPosition":0,"colorBorder":0,"sizeBorder":5,"opacityBorder":255,"colorText":-16703926,"isLock":false,"id":1742292801167,"rotate":-0,"matrix":"2.3877318,0.0,189.95352,0.0,2.3877318,756.26624,0.0,0.0,1.0","textOpacity":255,"rectCrop":"2,827148|15,000000|354,016602|75,000000","curve":0},{"type":"text","content":"SLOGAN HERE","inputContent":"SLOGAN HERE","sizePx":60,"fontName":"msc-font020!Numans-Regular!REGULAR!Regular","fontUrl":"https:\/\/raw.githubusercontent.com\/votaminh\/cdn.font.graphic\/main\/font_file4\/msc-font020Numans-RegularREGULARRegular","alignment":2,"isLower":false,"isBold":false,"isUnderline":false,"isItalic":false,"spacing":0.11999999731779099,"lineHeight":8,"colorShadow":0,"blurShadow":80,"opacityShadow":255,"offsetX":10,"offsetY":5,"borderPosition":0,"colorBorder":0,"sizeBorder":5,"opacityBorder":255,"colorText":-16703926,"isLock":false,"id":1742292803214,"rotate":-0,"matrix":"0.9882053,0.0,355.4051,0.0,0.9882053,953.94275,0.0,0.0,1.0","textOpacity":255,"rectCrop":"6,646875|0,908203|514,668335|44,707031","curve":0}],"width":1220,"height":1220,"ext":{}}