{"id":"green-circle-dot-and-white-hand","sticker":[{"type":"background","type_background":"Color","width":1220,"height":1220,"color_background":-12961222,"matrix":"1.0,0.0,0.0,0.0,1.0,0.0,0.0,0.0,1.0"},{"type":"drawable","color_fill":0,"opacity":255,"color_border":0,"size_border":0,"opacity_border":255,"isPhoto":false,"url":"https:\/\/raw.githubusercontent.com\/votaminh\/cdn.msc.logo\/main\/graphic_template\/logo-template-graphic\/business-consulting\/business-consulting-0025.svg","thumbUrl":"https:\/\/raw.githubusercontent.com\/votaminh\/cdn.msc.logo\/main\/graphic_template\/logo-template-graphic\/business-consulting\/business-consulting-0025.svg","matrix":"1.0,0.0,479.94238,0.0,1.0,337.96875,0.0,0.0,1.0","id":1735016153893,"rotate":-0,"originWidth":300,"originHeight":300,"currentWidth":258,"currentHeight":370,"lineStyle":0,"svgGradientConfig":{"svgGradients":[],"svgFillColors":[]},"rectCrop":"0,000000|0,000000|258,000000|370,000000","matrixCrop":"1.0,0.0,0.0,0.0,1.0,0.0,0.0,0.0,1.0","isLock":false},{"type":"drawable","color_fill":0,"opacity":255,"color_border":0,"size_border":0,"opacity_border":255,"isPhoto":false,"url":"https:\/\/raw.githubusercontent.com\/votaminh\/cdn.msc.logo\/main\/graphic_template\/logo-template-graphic\/linelae\/linelae-0070.svg","thumbUrl":"https:\/\/raw.githubusercontent.com\/votaminh\/cdn.msc.logo\/main\/graphic_template\/logo-template-graphic\/linelae\/linelae-0070.svg","matrix":"1.0,0.0,372.58237,0.0,1.0,224.56677,0.0,0.0,1.0","id":1735016154997,"rotate":-0,"originWidth":300,"originHeight":300,"currentWidth":473,"currentHeight":278,"lineStyle":0,"svgGradientConfig":{"svgGradients":[],"svgFillColors":[]},"rectCrop":"0,000000|0,000000|473,000000|278,000000","matrixCrop":"1.0,0.0,0.0,0.0,1.0,0.0,0.0,0.0,1.0","isLock":false},{"type":"text","content":"LOGO NAME","inputContent":"Logo Name","sizePx":60,"fontName":"YADXm3pZ1HU!Lato-Heavy!BOLD!Heavy","fontUrl":"https:\/\/raw.githubusercontent.com\/votaminh\/cdn.font.graphic\/main\/font_file4\/YADXm3pZ1HULato-HeavyBOLDHeavy","alignment":2,"isLower":false,"isBold":false,"isUnderline":false,"isItalic":false,"spacing":0.12999999523162842,"lineHeight":8,"colorShadow":0,"blurShadow":80,"opacityShadow":255,"offsetX":10,"offsetY":5,"borderPosition":0,"colorBorder":0,"sizeBorder":5,"opacityBorder":255,"colorText":-1,"isLock":false,"id":1735016156945,"rotate":-0,"matrix":"1.8012594,0.0,217.32544,0.0,1.8012594,781.48676,0.0,0.0,1.0","textOpacity":255,"rectCrop":"8,000000|0,000000|428,000000|43,000000","curve":0},{"type":"text","content":"SLOGAN HERE","inputContent":"Slogan Here","sizePx":60,"fontName":"YADXm3pZ1HU!Lato-Italic!ITALICS!Italic","fontUrl":"https:\/\/raw.githubusercontent.com\/votaminh\/cdn.font.graphic\/main\/font_file4\/YADXm3pZ1HULato-ItalicITALICSItalic","alignment":2,"isLower":false,"isBold":false,"isUnderline":false,"isItalic":false,"spacing":0.11999999731779099,"lineHeight":8,"colorShadow":0,"blurShadow":80,"opacityShadow":255,"offsetX":10,"offsetY":5,"borderPosition":0,"colorBorder":0,"sizeBorder":5,"opacityBorder":255,"colorText":-5329234,"isLock":false,"id":1735016158655,"rotate":-0,"matrix":"0.9856293,0.0,382.64966,0.0,0.9856293,911.909,0.0,0.0,1.0","textOpacity":255,"rectCrop":"4,000000|0,000000|455,000000|42,000000","curve":0}],"width":1220,"height":1220,"ext":{}}