{"id":"yellow-square-and-white-anchor","sticker":[{"type":"background","type_background":"Color","width":1220,"height":1220,"color_background":-1,"matrix":"1.0,0.0,0.0,0.0,1.0,0.0,0.0,0.0,1.0"},{"type":"drawable","color_fill":0,"opacity":255,"color_border":0,"size_border":0,"opacity_border":255,"isPhoto":false,"url":"https:\/\/raw.githubusercontent.com\/votaminh\/cdn.msc.logo\/main\/graphic_template\/logo-template-graphic\/shape\/shape-0777.svg","thumbUrl":"https:\/\/raw.githubusercontent.com\/votaminh\/cdn.msc.logo\/main\/graphic_template\/logo-template-graphic\/shape\/shape-0777.svg","matrix":"0.698313,0.7157924,117.32144,-0.7157924,0.698313,611.38965,0.0,0.0,1.0","id":1744085321888,"rotate":-45.70818328857422,"originWidth":300,"originHeight":300,"currentWidth":288,"currentHeight":288,"lineStyle":0,"svgGradientConfig":{"svgGradients":[],"svgFillColors":[]},"rectCrop":"0,000000|0,000000|288,000000|288,000000","matrixCrop":"1.0,0.0,0.0,0.0,1.0,0.0,0.0,0.0,1.0","isLock":false},{"type":"drawable","color_fill":0,"opacity":255,"color_border":0,"size_border":0,"opacity_border":255,"isPhoto":false,"url":"https:\/\/raw.githubusercontent.com\/votaminh\/cdn.msc.logo\/main\/graphic_template\/logo-template-graphic\/transportation\/transportation-0106.svg","thumbUrl":"https:\/\/raw.githubusercontent.com\/votaminh\/cdn.msc.logo\/main\/graphic_template\/logo-template-graphic\/transportation\/transportation-0106.svg","matrix":"1.0,0.0,208.46042,0.0,1.0,478.16495,0.0,0.0,1.0","id":1744085322549,"rotate":-0,"originWidth":300,"originHeight":300,"currentWidth":227,"currentHeight":261,"lineStyle":0,"svgGradientConfig":{"svgGradients":[],"svgFillColors":[]},"rectCrop":"0,000000|0,000000|227,000000|261,000000","matrixCrop":"1.0,0.0,0.0,0.0,1.0,0.0,0.0,0.0,1.0","isLock":false},{"type":"text","content":"LOGO NAME","inputContent":"LOGO NAME","sizePx":60,"fontName":"YACgEQY10lw!Oswald-Regular!REGULAR!Regular","fontUrl":"https:\/\/raw.githubusercontent.com\/votaminh\/cdn.font.graphic\/main\/font_file4\/YACgEQY10lwOswald-RegularREGULARRegular","alignment":2,"isLower":false,"isBold":false,"isUnderline":false,"isItalic":false,"spacing":0,"lineHeight":8,"colorShadow":0,"blurShadow":80,"opacityShadow":255,"offsetX":10,"offsetY":5,"borderPosition":0,"colorBorder":0,"sizeBorder":5,"opacityBorder":255,"colorText":-4419536,"isLock":false,"id":1744085324021,"rotate":-0,"matrix":"2.0519042,0.0,553.131,0.0,2.0519042,487.27887,0.0,0.0,1.0","textOpacity":255,"rectCrop":"3,779297|0,600586|258,375000|50,214844","curve":0},{"type":"text","content":"SLOGAN HERE","inputContent":"SLOGAN HERE","sizePx":60,"fontName":"YACgEQY10lw!Oswald-Regular!REGULAR!Regular","fontUrl":"https:\/\/raw.githubusercontent.com\/votaminh\/cdn.font.graphic\/main\/font_file4\/YACgEQY10lwOswald-RegularREGULARRegular","alignment":2,"isLower":false,"isBold":false,"isUnderline":false,"isItalic":false,"spacing":0.15000000596046448,"lineHeight":8,"colorShadow":0,"blurShadow":80,"opacityShadow":255,"offsetX":10,"offsetY":5,"borderPosition":0,"colorBorder":0,"sizeBorder":5,"opacityBorder":255,"colorText":-4419536,"isLock":false,"id":1744085324891,"rotate":-0,"matrix":"0.9999997,0.0,556.2982,0.0,0.9999997,639.38477,0.0,0.0,1.0","textOpacity":255,"rectCrop":"6,843750|0,600586|397,875000|50,214844","curve":0}],"width":1220,"height":1220,"ext":{}}