{"id":"orange-roaring-tiger","sticker":[{"type":"background","type_background":"Color","width":1220,"height":1220,"color_background":-16777133,"matrix":"1.0,0.0,0.0,0.0,1.0,0.0,0.0,0.0,1.0"},{"type":"drawable","color_fill":0,"opacity":255,"color_border":0,"size_border":0,"opacity_border":255,"isPhoto":false,"url":"https:\/\/raw.githubusercontent.com\/votaminh\/cdn.msc.logo\/main\/graphic_template\/logo-template-graphic\/badge\/badge-0106.svg","thumbUrl":"https:\/\/raw.githubusercontent.com\/votaminh\/cdn.msc.logo\/main\/graphic_template\/logo-template-graphic\/badge\/badge-0106.svg","matrix":"0.9999998,0.0,244.2702,0.0,0.9999998,242.92024,0.0,0.0,1.0","id":1737425521549,"rotate":-0,"originWidth":300,"originHeight":300,"currentWidth":732,"currentHeight":732,"lineStyle":0,"svgGradientConfig":{"svgGradients":[],"svgFillColors":[]},"rectCrop":"0,000000|0,000000|732,000000|732,000000","matrixCrop":"1.0,0.0,0.0,0.0,1.0,0.0,0.0,0.0,1.0","isLock":false},{"type":"drawable","color_fill":0,"opacity":255,"color_border":0,"size_border":0,"opacity_border":255,"isPhoto":false,"url":"https:\/\/raw.githubusercontent.com\/votaminh\/cdn.msc.logo\/main\/graphic_template\/logo-template-graphic\/animal-pet\/animal-pet-0183.svg","thumbUrl":"https:\/\/raw.githubusercontent.com\/votaminh\/cdn.msc.logo\/main\/graphic_template\/logo-template-graphic\/animal-pet\/animal-pet-0183.svg","matrix":"1.0,0.0,408.97018,0.0,1.0,489.90146,0.0,0.0,1.0","id":1737425522575,"rotate":-0,"originWidth":300,"originHeight":300,"currentWidth":402,"currentHeight":461,"lineStyle":0,"svgGradientConfig":{"svgGradients":[],"svgFillColors":[]},"rectCrop":"0,000000|0,000000|402,000000|461,000000","matrixCrop":"1.0,0.0,0.0,0.0,1.0,0.0,0.0,0.0,1.0","isLock":false},{"type":"text","content":"SLOGAN HERE","inputContent":"SLOGAN HERE","sizePx":60,"fontName":"YACgEQY10lw!Oswald-Regular!REGULAR!Regular","fontUrl":"https:\/\/raw.githubusercontent.com\/votaminh\/cdn.font.graphic\/main\/font_file4\/YACgEQY10lwOswald-RegularREGULARRegular","alignment":2,"isLower":false,"isBold":false,"isUnderline":false,"isItalic":false,"spacing":0.10000000149011612,"lineHeight":8,"colorShadow":0,"blurShadow":80,"opacityShadow":255,"offsetX":10,"offsetY":5,"borderPosition":0,"colorBorder":0,"sizeBorder":5,"opacityBorder":255,"colorText":-1283544,"isLock":false,"id":1737425524441,"rotate":-0,"matrix":"1.0321242,0.0,422.45187,0.0,1.0321242,310.078,0.0,0.0,1.0","textOpacity":255,"rectCrop":"5,000000|1,000000|366,000000|49,000000","curve":0},{"type":"text","content":"LOGO NAME","inputContent":"LOGO NAME","sizePx":60,"fontName":"msc-font019!Quantico-BoldItalic!BOLD_ITALICS!Bold_Italic","fontUrl":"https:\/\/raw.githubusercontent.com\/votaminh\/cdn.font.graphic\/main\/font_file4\/msc-font019Quantico-BoldItalicBOLD_ITALICSBold_Italic","alignment":2,"isLower":false,"isBold":false,"isUnderline":false,"isItalic":false,"spacing":0,"lineHeight":8,"colorShadow":0,"blurShadow":80,"opacityShadow":255,"offsetX":10,"offsetY":5,"borderPosition":0,"colorBorder":0,"sizeBorder":5,"opacityBorder":255,"colorText":-1,"isLock":false,"id":1737425526690,"rotate":-0,"matrix":"1.824662,0.0,299.43787,0.0,1.824662,419.89996,0.0,0.0,1.0","textOpacity":255,"rectCrop":"5,000000|0,000000|340,000000|42,000000","curve":0}],"width":1220,"height":1220,"ext":{}}