{"id":"opening-book-and-embroider-mortarboard","sticker":[{"type":"background","type_background":"Color","width":1220,"height":1220,"color_background":-1,"matrix":"1.0,0.0,0.0,0.0,1.0,0.0,0.0,0.0,1.0"},{"type":"drawable","color_fill":0,"opacity":255,"color_border":0,"size_border":0,"opacity_border":255,"isPhoto":false,"url":"https:\/\/raw.githubusercontent.com\/votaminh\/cdn.msc.logo\/main\/graphic_template\/logo-template-graphic\/education\/education-0426.svg","thumbUrl":"https:\/\/raw.githubusercontent.com\/votaminh\/cdn.msc.logo\/main\/graphic_template\/logo-template-graphic\/education\/education-0426.svg","matrix":"1.0,0.0,437.4572,0.0,1.0,342.29956,0.0,0.0,1.0","id":1737084947716,"rotate":-0,"originWidth":300,"originHeight":300,"currentWidth":346,"currentHeight":236,"lineStyle":0,"svgGradientConfig":{"svgGradients":[],"svgFillColors":[]},"rectCrop":"0,000000|0,000000|346,000000|236,000000","matrixCrop":"1.0,0.0,0.0,0.0,1.0,0.0,0.0,0.0,1.0","isLock":false},{"type":"drawable","color_fill":0,"opacity":255,"color_border":0,"size_border":0,"opacity_border":255,"isPhoto":false,"url":"https:\/\/raw.githubusercontent.com\/votaminh\/cdn.msc.logo\/main\/graphic_template\/logo-template-graphic\/education\/education-0425.svg","thumbUrl":"https:\/\/raw.githubusercontent.com\/votaminh\/cdn.msc.logo\/main\/graphic_template\/logo-template-graphic\/education\/education-0425.svg","matrix":"1.0,0.0,366.00006,0.0,1.0,494.39633,0.0,0.0,1.0","id":1737084948673,"rotate":-0,"originWidth":300,"originHeight":300,"currentWidth":488,"currentHeight":141,"lineStyle":0,"svgGradientConfig":{"svgGradients":[],"svgFillColors":[]},"rectCrop":"0,000000|0,000000|488,000000|141,000000","matrixCrop":"1.0,0.0,0.0,0.0,1.0,0.0,0.0,0.0,1.0","isLock":false},{"type":"drawable","color_fill":0,"opacity":255,"color_border":0,"size_border":0,"opacity_border":255,"isPhoto":false,"url":"https:\/\/raw.githubusercontent.com\/votaminh\/cdn.msc.logo\/main\/graphic_template\/logo-template-graphic\/linelae\/linelae-0550.svg","thumbUrl":"https:\/\/raw.githubusercontent.com\/votaminh\/cdn.msc.logo\/main\/graphic_template\/logo-template-graphic\/linelae\/linelae-0550.svg","matrix":"1.0,0.0,798.2286,0.0,1.0,831.69147,0.0,0.0,1.0","id":1737084949652,"rotate":-0,"originWidth":300,"originHeight":300,"currentWidth":73,"currentHeight":29,"lineStyle":0,"svgGradientConfig":{"svgGradients":[],"svgFillColors":[]},"rectCrop":"0,000000|0,000000|73,000000|29,000000","matrixCrop":"1.0,0.0,0.0,0.0,1.0,0.0,0.0,0.0,1.0","isLock":false},{"type":"drawable","color_fill":0,"opacity":255,"color_border":0,"size_border":0,"opacity_border":255,"isPhoto":false,"url":"https:\/\/raw.githubusercontent.com\/votaminh\/cdn.msc.logo\/main\/graphic_template\/logo-template-graphic\/linelae\/linelae-0550.svg","thumbUrl":"https:\/\/raw.githubusercontent.com\/votaminh\/cdn.msc.logo\/main\/graphic_template\/logo-template-graphic\/linelae\/linelae-0550.svg","matrix":"1.0,0.0,350.3143,0.0,1.0,831.69147,0.0,0.0,1.0","id":1737084950647,"rotate":-0,"originWidth":300,"originHeight":300,"currentWidth":73,"currentHeight":29,"lineStyle":0,"svgGradientConfig":{"svgGradients":[],"svgFillColors":[]},"rectCrop":"0,000000|0,000000|73,000000|29,000000","matrixCrop":"1.0,0.0,0.0,0.0,1.0,0.0,0.0,0.0,1.0","isLock":false},{"type":"text","content":"LOGO NAME","inputContent":"LOGO NAME","sizePx":60,"fontName":"YACgEYmuCJE!PlayfairDisplay-Bold!BOLD!Bold","fontUrl":"https:\/\/raw.githubusercontent.com\/votaminh\/cdn.font.graphic\/main\/font_file4\/YACgEYmuCJEPlayfairDisplay-BoldBOLDBold","alignment":2,"isLower":false,"isBold":false,"isUnderline":false,"isItalic":false,"spacing":0,"lineHeight":8,"colorShadow":0,"blurShadow":80,"opacityShadow":255,"offsetX":10,"offsetY":5,"borderPosition":0,"colorBorder":0,"sizeBorder":5,"opacityBorder":255,"colorText":-13421773,"isLock":false,"id":1737084953068,"rotate":-0,"matrix":"1.9581292,0.0,256.44397,0.0,1.9581292,701.65015,0.0,0.0,1.0","textOpacity":255,"rectCrop":"2,000000|0,000000|363,000000|44,000000","curve":0},{"type":"text","content":"SLOGAN HERE","inputContent":"SLOGAN HERE","sizePx":60,"fontName":"YADXm3pZ1HU!Lato-Regular!REGULAR!Regular","fontUrl":"https:\/\/raw.githubusercontent.com\/votaminh\/cdn.font.graphic\/main\/font_file4\/YADXm3pZ1HULato-RegularREGULARRegular","alignment":2,"isLower":false,"isBold":false,"isUnderline":false,"isItalic":false,"spacing":0,"lineHeight":8,"colorShadow":0,"blurShadow":80,"opacityShadow":255,"offsetX":10,"offsetY":5,"borderPosition":0,"colorBorder":0,"sizeBorder":5,"opacityBorder":255,"colorText":-13421773,"isLock":false,"id":1737084955238,"rotate":-0,"matrix":"0.8001352,0.0,447.4015,0.0,0.8001352,831.6917,0.0,0.0,1.0","textOpacity":255,"rectCrop":"2,000000|0,000000|407,000000|42,000000","curve":0}],"width":1220,"height":1220,"ext":{}}