{"id":"twined-rings-and-wedding","sticker":[{"type":"background","type_background":"Color","width":1220,"height":1220,"color_background":-16168881,"matrix":"1.0,0.0,0.0,0.0,1.0,0.0,0.0,0.0,1.0"},{"type":"drawable","color_fill":0,"opacity":255,"color_border":0,"size_border":0,"opacity_border":255,"isPhoto":false,"url":"https:\/\/raw.githubusercontent.com\/votaminh\/cdn.msc.logo\/main\/graphic_template\/logo-template-graphic\/shape\/shape-0602.svg","thumbUrl":"https:\/\/raw.githubusercontent.com\/votaminh\/cdn.msc.logo\/main\/graphic_template\/logo-template-graphic\/shape\/shape-0602.svg","matrix":"1.0,0.0,384.604,0.0,1.0,376.49768,0.0,0.0,1.0","id":1742975496542,"rotate":-0,"originWidth":300,"originHeight":300,"currentWidth":278,"currentHeight":278,"lineStyle":0,"svgGradientConfig":{"svgGradients":[],"svgFillColors":[]},"rectCrop":"0,000000|0,000000|278,000000|278,000000","matrixCrop":"1.0,0.0,0.0,0.0,1.0,0.0,0.0,0.0,1.0","isLock":false},{"type":"drawable","color_fill":0,"opacity":255,"color_border":0,"size_border":0,"opacity_border":255,"isPhoto":false,"url":"https:\/\/raw.githubusercontent.com\/votaminh\/cdn.msc.logo\/main\/graphic_template\/logo-template-graphic\/shape\/shape-0602.svg","thumbUrl":"https:\/\/raw.githubusercontent.com\/votaminh\/cdn.msc.logo\/main\/graphic_template\/logo-template-graphic\/shape\/shape-0602.svg","matrix":"1.0,0.0,560.9568,0.0,1.0,376.5382,0.0,0.0,1.0","id":1742975497213,"rotate":-0,"originWidth":300,"originHeight":300,"currentWidth":278,"currentHeight":278,"lineStyle":0,"svgGradientConfig":{"svgGradients":[],"svgFillColors":[]},"rectCrop":"0,000000|0,000000|278,000000|278,000000","matrixCrop":"1.0,0.0,0.0,0.0,1.0,0.0,0.0,0.0,1.0","isLock":false},{"type":"drawable","color_fill":0,"opacity":255,"color_border":0,"size_border":0,"opacity_border":255,"isPhoto":false,"url":"https:\/\/raw.githubusercontent.com\/votaminh\/cdn.msc.logo\/main\/graphic_template\/logo-template-graphic\/love\/love-0086.svg","thumbUrl":"https:\/\/raw.githubusercontent.com\/votaminh\/cdn.msc.logo\/main\/graphic_template\/logo-template-graphic\/love\/love-0086.svg","matrix":"1.0,0.0,548.75684,0.0,1.0,276.55875,0.0,0.0,1.0","id":1742975497882,"rotate":-0,"originWidth":300,"originHeight":300,"currentWidth":122,"currentHeight":100,"lineStyle":0,"svgGradientConfig":{"svgGradients":[],"svgFillColors":[]},"rectCrop":"0,000000|0,000000|122,000000|100,000000","matrixCrop":"1.0,0.0,0.0,0.0,1.0,0.0,0.0,0.0,1.0","isLock":false},{"type":"text","content":"LOGO NAME","inputContent":"LOGO NAME","sizePx":60,"fontName":"YALBs0MvhmA!Oranienbaum-Regular!REGULAR!Regular","fontUrl":"https:\/\/raw.githubusercontent.com\/votaminh\/cdn.font.graphic\/main\/font_file4\/YALBs0MvhmAOranienbaum-RegularREGULARRegular","alignment":2,"isLower":false,"isBold":false,"isUnderline":false,"isItalic":false,"spacing":0.1599999964237213,"lineHeight":8,"colorShadow":0,"blurShadow":80,"opacityShadow":255,"offsetX":10,"offsetY":5,"borderPosition":0,"colorBorder":0,"sizeBorder":5,"opacityBorder":255,"colorText":-1,"isLock":false,"id":1742975500412,"rotate":-0,"matrix":"2.3739781,0.0,181.54884,0.0,2.3739781,718.27185,0.0,0.0,1.0","textOpacity":255,"rectCrop":"7,495312|0,893555|357,998444|44,692383","curve":0},{"type":"text","content":"SLOGAN HERE","inputContent":"SLOGAN HERE","sizePx":60,"fontName":"YACgEYmuCJE!PlayfairDisplay-Regular!REGULAR!Regular","fontUrl":"https:\/\/raw.githubusercontent.com\/votaminh\/cdn.font.graphic\/main\/font_file4\/YACgEYmuCJEPlayfairDisplay-RegularREGULARRegular","alignment":2,"isLower":false,"isBold":false,"isUnderline":false,"isItalic":false,"spacing":0.17000000178813934,"lineHeight":8,"colorShadow":0,"blurShadow":80,"opacityShadow":255,"offsetX":10,"offsetY":5,"borderPosition":0,"colorBorder":0,"sizeBorder":5,"opacityBorder":255,"colorText":-1,"isLock":false,"id":1742975502196,"rotate":-0,"matrix":"0.95373565,0.0,367.58417,0.0,0.95373565,883.10864,0.0,0.0,1.0","textOpacity":255,"rectCrop":"8,879297|0,834961|508,562866|44,985352","curve":0},{"type":"text","content":"&","inputContent":"&","sizePx":60,"fontName":"YACgEYmuCJE!PlayfairDisplay-Regular!REGULAR!Regular","fontUrl":"https:\/\/raw.githubusercontent.com\/votaminh\/cdn.font.graphic\/main\/font_file4\/YACgEYmuCJEPlayfairDisplay-RegularREGULARRegular","alignment":2,"isLower":true,"isBold":false,"isUnderline":false,"isItalic":false,"spacing":0,"lineHeight":8,"colorShadow":0,"blurShadow":80,"opacityShadow":255,"offsetX":10,"offsetY":5,"borderPosition":0,"colorBorder":0,"sizeBorder":5,"opacityBorder":255,"colorText":-350430,"isLock":false,"id":1742975503913,"rotate":-0,"matrix":"1.0640079,0.0,582.2024,0.0,1.0640079,492.5748,0.0,0.0,1.0","textOpacity":255,"rectCrop":"3,237305|0,834961|49,013672|44,985352","curve":0},{"type":"text","content":"L","inputContent":"L","sizePx":60,"fontName":"YACgEYmuCJE!PlayfairDisplay-Regular!REGULAR!Regular","fontUrl":"https:\/\/raw.githubusercontent.com\/votaminh\/cdn.font.graphic\/main\/font_file4\/YACgEYmuCJEPlayfairDisplay-RegularREGULARRegular","alignment":2,"isLower":true,"isBold":false,"isUnderline":false,"isItalic":false,"spacing":0,"lineHeight":8,"colorShadow":0,"blurShadow":80,"opacityShadow":255,"offsetX":10,"offsetY":5,"borderPosition":0,"colorBorder":0,"sizeBorder":5,"opacityBorder":255,"colorText":-350430,"isLock":false,"id":1742975515322,"rotate":-0,"matrix":"1.6950938,0.0,462.51358,0.0,1.6950938,485.06253,0.0,0.0,1.0","textOpacity":255,"rectCrop":"2,519531|0,000000|33,662109|42,480469","curve":0},{"type":"text","content":"N","inputContent":"N","sizePx":60,"fontName":"YACgEYmuCJE!PlayfairDisplay-Regular!REGULAR!Regular","fontUrl":"https:\/\/raw.githubusercontent.com\/votaminh\/cdn.font.graphic\/main\/font_file4\/YACgEYmuCJEPlayfairDisplay-RegularREGULARRegular","alignment":2,"isLower":true,"isBold":false,"isUnderline":false,"isItalic":false,"spacing":0,"lineHeight":8,"colorShadow":0,"blurShadow":80,"opacityShadow":255,"offsetX":10,"offsetY":5,"borderPosition":0,"colorBorder":0,"sizeBorder":5,"opacityBorder":255,"colorText":-350430,"isLock":false,"id":1742975584490,"rotate":-0,"matrix":"1.6950938,0.0,703.0403,0.0,1.6950938,484.56598,0.0,0.0,1.0","textOpacity":255,"rectCrop":"2,519531|0,292969|40,195313|43,066406","curve":0},{"type":"line","size":7,"color":-1,"opacity":255,"startX":0,"startY":51,"endX":569,"endY":51,"lineStyle":0,"id":1742975596704,"isLock":false,"matrix":"0.9999998,0.0,325.5001,0.0,0.9999998,803.5731,0.0,0.0,1.0"}],"width":1220,"height":1220,"ext":{}}