{"id":"red-cross-banner-and-hand","sticker":[{"type":"background","type_background":"Color","width":1220,"height":1220,"color_background":-1,"matrix":"1.0,0.0,0.0,0.0,1.0,0.0,0.0,0.0,1.0"},{"type":"drawable","color_fill":0,"opacity":255,"color_border":0,"size_border":0,"opacity_border":255,"isPhoto":false,"url":"https:\/\/raw.githubusercontent.com\/votaminh\/cdn.msc.logo\/main\/graphic_template\/logo-template-graphic\/shape\/shape-1350.svg","thumbUrl":"https:\/\/raw.githubusercontent.com\/votaminh\/cdn.msc.logo\/main\/graphic_template\/logo-template-graphic\/shape\/shape-1350.svg","matrix":"1.0,0.0,231.8,0.0,1.0,231.8,0.0,0.0,1.0","id":1741317367234,"rotate":-0,"originWidth":300,"originHeight":300,"currentWidth":756,"currentHeight":756,"lineStyle":0,"svgGradientConfig":{"svgGradients":[],"svgFillColors":[]},"rectCrop":"0,000000|0,000000|756,000000|756,000000","matrixCrop":"1.0,0.0,0.0,0.0,1.0,0.0,0.0,0.0,1.0","isLock":false},{"type":"drawable","color_fill":0,"opacity":255,"color_border":0,"size_border":0,"opacity_border":255,"isPhoto":false,"url":"https:\/\/raw.githubusercontent.com\/votaminh\/cdn.msc.logo\/main\/graphic_template\/logo-template-graphic\/music\/music-0350.svg","thumbUrl":"https:\/\/raw.githubusercontent.com\/votaminh\/cdn.msc.logo\/main\/graphic_template\/logo-template-graphic\/music\/music-0350.svg","matrix":"1.0,0.0,448.5611,0.0,1.0,535.0571,0.0,0.0,1.0","id":1741317367981,"rotate":-0,"originWidth":300,"originHeight":300,"currentWidth":146,"currentHeight":236,"lineStyle":0,"svgGradientConfig":{"svgGradients":[],"svgFillColors":[]},"rectCrop":"0,000000|0,000000|146,000000|236,000000","matrixCrop":"1.0,0.0,0.0,0.0,1.0,0.0,0.0,0.0,1.0","isLock":false},{"type":"drawable","color_fill":0,"opacity":255,"color_border":0,"size_border":0,"opacity_border":255,"isPhoto":false,"url":"https:\/\/raw.githubusercontent.com\/votaminh\/cdn.msc.logo\/main\/graphic_template\/logo-template-graphic\/banner\/banner-0280.svg","thumbUrl":"https:\/\/raw.githubusercontent.com\/votaminh\/cdn.msc.logo\/main\/graphic_template\/logo-template-graphic\/banner\/banner-0280.svg","matrix":"1.0162091,0.0,81.91431,0.0,1.0162091,724.5175,0.0,0.0,1.0","id":1741317368715,"rotate":-0,"originWidth":300,"originHeight":300,"currentWidth":1056,"currentHeight":209,"lineStyle":0,"svgGradientConfig":{"svgGradients":[],"svgFillColors":[]},"rectCrop":"0,000000|0,000000|1056,000000|209,000000","matrixCrop":"1.0,0.0,0.0,0.0,1.0,0.0,0.0,0.0,1.0","isLock":false},{"type":"drawable","color_fill":0,"opacity":255,"color_border":0,"size_border":0,"opacity_border":255,"isPhoto":false,"url":"https:\/\/raw.githubusercontent.com\/votaminh\/cdn.msc.logo\/main\/graphic_template\/logo-template-graphic\/music\/music-0349.svg","thumbUrl":"https:\/\/raw.githubusercontent.com\/votaminh\/cdn.msc.logo\/main\/graphic_template\/logo-template-graphic\/music\/music-0349.svg","matrix":"1.0,0.0,468.0512,0.0,1.0,385.17145,0.0,0.0,1.0","id":1741317369830,"rotate":-0,"originWidth":300,"originHeight":300,"currentWidth":334,"currentHeight":336,"lineStyle":0,"svgGradientConfig":{"svgGradients":[],"svgFillColors":[]},"rectCrop":"0,000000|0,000000|334,000000|336,000000","matrixCrop":"1.0,0.0,0.0,0.0,1.0,0.0,0.0,0.0,1.0","isLock":false},{"type":"drawable","color_fill":0,"opacity":255,"color_border":0,"size_border":0,"opacity_border":255,"isPhoto":false,"url":"https:\/\/raw.githubusercontent.com\/votaminh\/cdn.msc.logo\/main\/graphic_template\/logo-template-graphic\/star\/star-0265.svg","thumbUrl":"https:\/\/raw.githubusercontent.com\/votaminh\/cdn.msc.logo\/main\/graphic_template\/logo-template-graphic\/star\/star-0265.svg","matrix":"1.0,0.0,914.6516,0.0,1.0,554.2286,0.0,0.0,1.0","id":1741317371905,"rotate":-0,"originWidth":300,"originHeight":300,"currentWidth":43,"currentHeight":134,"lineStyle":0,"svgGradientConfig":{"svgGradients":[],"svgFillColors":[]},"rectCrop":"0,000000|0,000000|43,000000|134,000000","matrixCrop":"1.0,0.0,0.0,0.0,1.0,0.0,0.0,0.0,1.0","isLock":false},{"type":"drawable","color_fill":0,"opacity":255,"color_border":0,"size_border":0,"opacity_border":255,"isPhoto":false,"url":"https:\/\/raw.githubusercontent.com\/votaminh\/cdn.msc.logo\/main\/graphic_template\/logo-template-graphic\/star\/star-0265.svg","thumbUrl":"https:\/\/raw.githubusercontent.com\/votaminh\/cdn.msc.logo\/main\/graphic_template\/logo-template-graphic\/star\/star-0265.svg","matrix":"1.0,0.0,261.08005,0.0,1.0,554.2286,0.0,0.0,1.0","id":1741317375345,"rotate":-0,"originWidth":300,"originHeight":300,"currentWidth":43,"currentHeight":134,"lineStyle":0,"svgGradientConfig":{"svgGradients":[],"svgFillColors":[]},"rectCrop":"0,000000|0,000000|43,000000|134,000000","matrixCrop":"-1.0,0.0,43.0,0.0,1.0,0.0,0.0,0.0,1.0","isLock":false},{"type":"text","content":"Logo Name","inputContent":"Logo Name","sizePx":60,"fontName":"YAEe9XbWpNs!CinzelDecorative-Bold!BOLD!Bold","fontUrl":"https:\/\/raw.githubusercontent.com\/votaminh\/cdn.font.graphic\/main\/font_file4\/YAEe9XbWpNsCinzelDecorative-BoldBOLDBold","alignment":2,"isLower":true,"isBold":false,"isUnderline":false,"isItalic":false,"spacing":0.03999999910593033,"lineHeight":8,"colorShadow":0,"blurShadow":80,"opacityShadow":255,"offsetX":10,"offsetY":5,"borderPosition":0,"colorBorder":0,"sizeBorder":5,"opacityBorder":255,"colorText":-13882836,"isLock":false,"id":1741317378982,"rotate":-0,"matrix":"1.7492394,0.0,256.0347,0.0,1.7492394,777.52325,0.0,0.0,1.0","textOpacity":255,"rectCrop":"3,719531|14,458008|405,097260|79,189453","curve":0},{"type":"text","content":"SLOGAN HERE","inputContent":"SLOGAN HERE","sizePx":60,"fontName":"YACgEan-tYE!RobotoCondensed-Regular!REGULAR!Regular","fontUrl":"https:\/\/raw.githubusercontent.com\/votaminh\/cdn.font.graphic\/main\/font_file4\/YACgEan-tYERobotoCondensed-RegularREGULARRegular","alignment":2,"isLower":false,"isBold":false,"isUnderline":false,"isItalic":false,"spacing":0.38999998569488525,"lineHeight":8,"colorShadow":0,"blurShadow":80,"opacityShadow":255,"offsetX":10,"offsetY":5,"borderPosition":0,"colorBorder":0,"sizeBorder":5,"opacityBorder":255,"colorText":-1,"isLock":false,"id":1741317381382,"rotate":-1.224822998046875,"matrix":"1.0275058,0.021968536,299.06995,-0.021968536,1.0275058,270.88135,0.0,0.0,1.0","textOpacity":255,"rectCrop":"23,074310|0,585938|578,452637|171,829971","curve":16}],"width":1220,"height":1220,"ext":{}}