{"id":"white-and-red-building","sticker":[{"type":"background","type_background":"Color","width":1220,"height":1220,"color_background":-1,"matrix":"1.0,0.0,0.0,0.0,1.0,0.0,0.0,0.0,1.0"},{"type":"drawable","color_fill":0,"opacity":255,"color_border":0,"size_border":0,"opacity_border":255,"isPhoto":false,"url":"https:\/\/raw.githubusercontent.com\/votaminh\/cdn.msc.logo\/main\/graphic_template\/logo-template-graphic\/construction\/construction-0124.svg","thumbUrl":"https:\/\/raw.githubusercontent.com\/votaminh\/cdn.msc.logo\/main\/graphic_template\/logo-template-graphic\/construction\/construction-0124.svg","matrix":"1.0,0.0,409.9201,0.0,1.0,412.48428,0.0,0.0,1.0","id":1743157023678,"rotate":-0,"originWidth":300,"originHeight":300,"currentWidth":400,"currentHeight":119,"lineStyle":0,"svgGradientConfig":{"svgGradients":[{"id":"grad1743157035366","x1":"0.98130965","y1":"0.48882586","x2":"0.048262637","y2":"0.492031","offset1":"0.0%","color1":"#680003","offset2":"100.0%","color2":"#D30006"}],"svgFillColors":[{"fillColor":"grad1743157035366","targetColorHex":"#9F0005"}]},"rectCrop":"0,000000|0,000000|400,000000|119,000000","matrixCrop":"1.0,0.0,0.0,0.0,1.0,0.0,0.0,0.0,1.0","isLock":false},{"type":"text","content":"Company Name","inputContent":"Company Name","sizePx":60,"fontName":"YAEe9XbWpNs!CinzelDecorative-Regular!REGULAR!Regular","fontUrl":"https:\/\/raw.githubusercontent.com\/votaminh\/cdn.font.graphic\/main\/font_file4\/YAEe9XbWpNsCinzelDecorative-RegularREGULARRegular","alignment":2,"isLower":true,"isBold":false,"isUnderline":false,"isItalic":false,"spacing":0,"lineHeight":8,"colorShadow":0,"blurShadow":80,"opacityShadow":255,"offsetX":10,"offsetY":5,"borderPosition":0,"colorBorder":0,"sizeBorder":5,"opacityBorder":255,"colorText":-16777216,"isLock":false,"id":1743157038599,"rotate":-0,"matrix":"1.7094908,0.0,172.79959,0.0,1.7094908,558.1366,0.0,0.0,1.0","textOpacity":255,"rectCrop":"2,695313|10,620117|516,321289|71,279297","curve":0},{"type":"text","content":"SLOGAN HERE","inputContent":"SLOGAN HERE","sizePx":60,"fontName":"YADXm3pZ1HU!Lato-Regular!REGULAR!Regular","fontUrl":"https:\/\/raw.githubusercontent.com\/votaminh\/cdn.font.graphic\/main\/font_file4\/YADXm3pZ1HULato-RegularREGULARRegular","alignment":2,"isLower":false,"isBold":false,"isUnderline":false,"isItalic":false,"spacing":0.20999999344348907,"lineHeight":8,"colorShadow":0,"blurShadow":80,"opacityShadow":255,"offsetX":10,"offsetY":5,"borderPosition":0,"colorBorder":0,"sizeBorder":5,"opacityBorder":255,"colorText":-10592674,"isLock":false,"id":1743157039483,"rotate":-0,"matrix":"0.86001265,0.0,372.82288,0.0,0.86001265,753.7141,0.0,0.0,1.0","textOpacity":255,"rectCrop":"8,277538|0,483398|538,935791|44,443359","curve":0},{"type":"shape","shapeType":1,"opacity":255,"color":0,"opacityBorder":255,"colorBorder":0,"sizeBorder":0,"corner":0,"lineStyle":0,"rectBound":"0,000000|586,422119|610,000000|596,113647","id":1743157063685,"matrix":"0.9570528,0.0,319.552,0.0,0.9570528,143.02087,0.0,0.0,1.0","gradient":{"startColor":-9961469,"endColor":-2949114,"offset1":0,"offset2":100,"percentX1":0,"percentY1":0.5,"percentX2":1,"percentY2":0.5}},{"type":"shape","shapeType":1,"opacity":255,"color":0,"opacityBorder":255,"colorBorder":0,"sizeBorder":0,"corner":0,"lineStyle":0,"rectBound":"0,000000|586,422119|610,000000|596,113647","id":1743157084063,"matrix":"0.9570528,0.0,318.09894,0.0,0.9570528,-21.513,0.0,0.0,1.0","gradient":{"startColor":-9961469,"endColor":-2949114,"offset1":0,"offset2":100,"percentX1":0,"percentY1":0.5,"percentX2":1,"percentY2":0.5}}],"width":1220,"height":1220,"ext":{}}