{"id":"white-surfboard-and-wave","sticker":[{"type":"background","type_background":"Color","width":1220,"height":1220,"color_background":-14458429,"matrix":"1.0,0.0,0.0,0.0,1.0,0.0,0.0,0.0,1.0"},{"type":"drawable","color_fill":0,"opacity":255,"color_border":0,"size_border":0,"opacity_border":255,"isPhoto":false,"url":"https:\/\/raw.githubusercontent.com\/votaminh\/cdn.msc.logo\/main\/graphic_template\/logo-template-graphic\/sports-fitness\/sports-fitness-0992.svg","thumbUrl":"https:\/\/raw.githubusercontent.com\/votaminh\/cdn.msc.logo\/main\/graphic_template\/logo-template-graphic\/sports-fitness\/sports-fitness-0992.svg","matrix":"1.0,0.0,545.85834,0.0,1.0,258.84555,0.0,0.0,1.0","id":1743565172797,"rotate":-0,"originWidth":300,"originHeight":300,"currentWidth":126,"currentHeight":348,"lineStyle":0,"svgGradientConfig":{"svgGradients":[],"svgFillColors":[]},"rectCrop":"0,000000|0,000000|126,000000|348,000000","matrixCrop":"1.0,0.0,0.0,0.0,1.0,0.0,0.0,0.0,1.0","isLock":false},{"type":"drawable","color_fill":0,"opacity":255,"color_border":0,"size_border":0,"opacity_border":255,"isPhoto":false,"url":"https:\/\/raw.githubusercontent.com\/votaminh\/cdn.msc.logo\/main\/graphic_template\/logo-template-graphic\/nature\/nature-1213.svg","thumbUrl":"https:\/\/raw.githubusercontent.com\/votaminh\/cdn.msc.logo\/main\/graphic_template\/logo-template-graphic\/nature\/nature-1213.svg","matrix":"1.0,0.0,393.35825,0.0,1.0,551.2087,0.0,0.0,1.0","id":1743565173499,"rotate":-0,"originWidth":300,"originHeight":300,"currentWidth":431,"currentHeight":155,"lineStyle":0,"svgGradientConfig":{"svgGradients":[],"svgFillColors":[]},"rectCrop":"0,000000|0,000000|431,000000|155,000000","matrixCrop":"1.0,0.0,0.0,0.0,1.0,0.0,0.0,0.0,1.0","isLock":false},{"type":"text","content":"COMPANY NAME","inputContent":"COMPANY NAME","sizePx":60,"fontName":"YALBsyapvaU!Jura-Bold!REGULAR!Bold","fontUrl":"https:\/\/raw.githubusercontent.com\/votaminh\/cdn.font.graphic\/main\/font_file4\/YALBsyapvaUJura-BoldREGULARBold","alignment":2,"isLower":false,"isBold":false,"isUnderline":false,"isItalic":false,"spacing":0,"lineHeight":8,"colorShadow":0,"blurShadow":80,"opacityShadow":255,"offsetX":10,"offsetY":5,"borderPosition":0,"colorBorder":0,"sizeBorder":5,"opacityBorder":255,"colorText":-1,"isLock":false,"id":1743565174906,"rotate":-0,"matrix":"1.9685771,0.0,142.06155,0.0,1.9685771,796.1946,0.0,0.0,1.0","textOpacity":255,"rectCrop":"4,804688|0,000000|478,225586|40,737305","curve":0},{"type":"text","content":"SLOGAN HERE","inputContent":"SLOGAN HERE","sizePx":60,"fontName":"YALBs3fn634!Jura-Medium!REGULAR!Medium","fontUrl":"https:\/\/raw.githubusercontent.com\/votaminh\/cdn.font.graphic\/main\/font_file4\/YALBs3fn634Jura-MediumREGULARMedium","alignment":2,"isLower":false,"isBold":false,"isUnderline":false,"isItalic":false,"spacing":0.009999999776482582,"lineHeight":8,"colorShadow":0,"blurShadow":80,"opacityShadow":255,"offsetX":10,"offsetY":5,"borderPosition":0,"colorBorder":0,"sizeBorder":5,"opacityBorder":255,"colorText":-1,"isLock":false,"id":1743565175802,"rotate":-0,"matrix":"0.9167701,0.0,422.59222,0.0,0.9167701,921.91516,0.0,0.0,1.0","textOpacity":255,"rectCrop":"5,046094|0,424805|401,843933|40,151367","curve":0}],"width":1220,"height":1220,"ext":{}}