{"ext":{},"sticker":[{"type_background":"Color","color_background":-11259879,"width":1220,"type":"background","matrix":"1.0,0.0,0.0,0.0,1.0,0.0,0.0,0.0,1.0","height":1220},{"size_border":0,"rotate":-0,"originHeight":300,"color_fill":0,"originWidth":300,"opacity_border":255,"isPhoto":false,"type":"drawable","matrix":"0.8979479,0.0,451.02893,0.0,0.8979479,484.58438,0.0,0.0,1.0","color_border":0,"url":"https://raw.githubusercontent.com/votaminh/cdn.msc.logo/main/graphic_template/logo-template-graphic/food-drink/food-drink-0303.svg","isLock":false,"lineStyle":0,"currentWidth":300,"matrixCrop":"1.0,0.0,0.0,0.0,1.0,0.0,0.0,0.0,1.0","currentHeight":68,"rectCrop":"0,000000|0,000000|300,000000|68,000000","id":1729235560298,"opacity":255,"thumbUrl":"https://raw.githubusercontent.com/votaminh/cdn.msc.logo/main/graphic_template/logo-template-graphic/food-drink/food-drink-0303.svg","svgGradientConfig":{"svgGradients":[],"svgFillColors":[]}},{"size_border":0,"rotate":-0,"originHeight":300,"color_fill":0,"originWidth":300,"opacity_border":255,"isPhoto":false,"type":"drawable","matrix":"0.32531983,0.0,536.92316,0.0,0.32531983,196.85426,0.0,0.0,1.0","color_border":0,"url":"https://raw.githubusercontent.com/votaminh/cdn.msc.logo/main/graphic_template/logo-template-graphic/food-drink/food-drink-0301.svg","isLock":false,"lineStyle":0,"currentWidth":300,"matrixCrop":"1.0,0.0,0.0,0.0,1.0,0.0,0.0,0.0,1.0","currentHeight":557,"rectCrop":"0,000000|0,000000|300,000000|557,000000","id":1729235568331,"opacity":255,"thumbUrl":"https://raw.githubusercontent.com/votaminh/cdn.msc.logo/main/graphic_template/logo-template-graphic/food-drink/food-drink-0301.svg","svgGradientConfig":{"svgGradients":[],"svgFillColors":[]}},{"size_border":0,"rotate":-0,"originHeight":300,"color_fill":0,"originWidth":300,"opacity_border":255,"isPhoto":false,"type":"drawable","matrix":"1.1840936,0.0,431.904,0.0,1.1840936,393.4219,0.0,0.0,1.0","color_border":0,"url":"https://raw.githubusercontent.com/votaminh/cdn.msc.logo/main/graphic_template/logo-template-graphic/food-drink/food-drink-0302.svg","isLock":false,"lineStyle":0,"currentWidth":300,"matrixCrop":"1.0,0.0,0.0,0.0,1.0,0.0,0.0,0.0,1.0","currentHeight":240,"rectCrop":"0,000000|0,000000|300,000000|240,000000","id":1729235581450,"opacity":255,"thumbUrl":"https://raw.githubusercontent.com/votaminh/cdn.msc.logo/main/graphic_template/logo-template-graphic/food-drink/food-drink-0302.svg","svgGradientConfig":{"svgGradients":[],"svgFillColors":[]}},{"opacityShadow":255,"rotate":-0,"isUnderline":false,"curve":0,"fontUrl":"https://raw.githubusercontent.com/votaminh/cdn.font.graphic/main/font_file4/YACgEckzDrAGrandHotel-RegularREGULARRegular","type":"text","matrix":"2.5748184,0.0,178.87543,0.0,2.5748184,699.4504,0.0,0.0,1.0","content":"Company Name","inputContent":"Company Name","isItalic":false,"offsetX":10,"isLock":false,"blurShadow":80,"spacing":0.05999999865889549,"offsetY":5,"sizePx":60,"rectCrop":"4,000000|24,000000|339,000000|91,000000","id":1729235591517,"colorText":-1827,"opacityBorder":255,"sizeBorder":5,"colorBorder":0,"isBold":false,"fontName":"YACgEckzDrA!GrandHotel-Regular!REGULAR!Regular","isLower":true,"colorShadow":0,"textOpacity":255,"lineHeight":8,"alignment":2,"borderPosition":0},{"opacityShadow":255,"rotate":-0,"isUnderline":false,"curve":0,"fontUrl":"https://raw.githubusercontent.com/votaminh/cdn.font.graphic/main/font_file4/YACgEQzTv38SourceSansPro-RegularREGULARRegular","type":"text","matrix":"0.90278345,0.0,429.92105,0.0,0.90278345,968.32263,0.0,0.0,1.0","content":"SLOGAN HERE","inputContent":"Slogan Here","isItalic":false,"offsetX":10,"isLock":false,"blurShadow":80,"spacing":0.07000000029802322,"offsetY":5,"sizePx":60,"rectCrop":"4,000000|0,000000|397,000000|40,000000","id":1729235641023,"colorText":-2575740,"opacityBorder":255,"sizeBorder":5,"colorBorder":0,"isBold":false,"fontName":"YACgEQzTv38!SourceSansPro-Regular!REGULAR!Regular","isLower":false,"colorShadow":0,"textOpacity":255,"lineHeight":8,"alignment":2,"borderPosition":0}],"width":1220,"id":"beige-cup-and-chocolate-hot-coffee","height":1220}